if/__init__.py
if-0.0.5.dist-info/LICENSE
if-0.0.5.dist-info/METADATA
if-0.0.5.dist-info/WHEEL
if-0.0.5.dist-info/top_level.txt
if-0.0.5.dist-info/RECORD
