Metadata-Version: 2.1
Name: if
Version: 0.0.5
Summary: Face-lift makeing BeautifulSoup even more beautiful
Home-page: https://github.com/thorwhalen/uu/tree/master/if
Author: Thor Whalen
License: apache-2.0
Platform: any
License-File: LICENSE
